jsonschema2popo/__init__.py
jsonschema2popo/__main__.py
jsonschema2popo/_class.tmpl
jsonschema2popo/jsonschema2popo.py
jsonschema2popo-0.12.dist-info/DESCRIPTION.rst
jsonschema2popo-0.12.dist-info/METADATA
jsonschema2popo-0.12.dist-info/RECORD
jsonschema2popo-0.12.dist-info/WHEEL
jsonschema2popo-0.12.dist-info/entry_points.txt
jsonschema2popo-0.12.dist-info/metadata.json
jsonschema2popo-0.12.dist-info/top_level.txt
