Metadata-Version: 2.1
Name: jsonschema2popo
Version: 0.12
Summary: Converts a JSON Schema to a Plain Old Python Object class
Home-page: https://github.com/frx08/jsonschema2popo
Author: cruc.io
Author-email: frx089@gmail.com
License: MIT License
Keywords: python json-schema code-generator
Platform: UNKNOWN
Classifier: Development Status :: 5 - Production/Stable
Classifier: Intended Audience :: Developers
Classifier: License :: OSI Approved :: MIT License
Classifier: Topic :: Software Development :: Build Tools
Classifier: Programming Language :: Python :: 3.4
Classifier: Programming Language :: Python :: 3.5
Classifier: Programming Language :: Python :: 3.6
Classifier: Programming Language :: Python :: Implementation :: PyPy
Requires-Python: >=3.4
